wyoming_faster_whisper/__init__.py
wyoming_faster_whisper/__main__.py
wyoming_faster_whisper/const.py
wyoming_faster_whisper/dispatch_handler.py
wyoming_faster_whisper/faster_whisper_handler.py
wyoming_faster_whisper/models.py
wyoming_faster_whisper/onnx_asr_handler.py
wyoming_faster_whisper/sherpa_handler.py
wyoming_faster_whisper/transformers_whisper.py
wyoming_faster_whisper-3.1.0.dist-info/licenses/LICENSE.md
wyoming_faster_whisper-3.1.0.dist-info/METADATA
wyoming_faster_whisper-3.1.0.dist-info/WHEEL
wyoming_faster_whisper-3.1.0.dist-info/entry_points.txt
wyoming_faster_whisper-3.1.0.dist-info/top_level.txt
wyoming_faster_whisper-3.1.0.dist-info/zip-safe
wyoming_faster_whisper-3.1.0.dist-info/RECORD
