Metadata-Version: 2.4
Name: wyoming-faster-whisper
Version: 3.1.0
Summary: Wyoming Server for Faster Whisper
Author-email: Michael Hansen <mike@rhasspy.org>
License: MIT
Project-URL: Homepage, http://github.com/rhasspy/wyoming-faster-whisper
Keywords: rhasspy,wyoming,whisper,stt
Platform: any
Classifier: Development Status :: 3 - Alpha
Classifier: Intended Audience :: Developers
Classifier: Topic :: Multimedia :: Sound/Audio :: Speech
Classifier: License :: OSI Approved :: MIT License
Classifier: Programming Language :: Python :: 3.8
Classifier: Programming Language :: Python :: 3.9
Classifier: Programming Language :: Python :: 3.10
Classifier: Programming Language :: Python :: 3.11
Classifier: Programming Language :: Python :: 3.12
Classifier: Programming Language :: Python :: 3.13
Requires-Python: >=3.8
License-File: LICENSE.md
Requires-Dist: wyoming<2,>=1.8
Requires-Dist: faster-whisper<2,>=1.1.0
Requires-Dist: requests
Provides-Extra: dev
Requires-Dist: black; extra == "dev"
Requires-Dist: flake8; extra == "dev"
Requires-Dist: isort; extra == "dev"
Requires-Dist: mypy; extra == "dev"
Requires-Dist: pylint; extra == "dev"
Requires-Dist: pytest; extra == "dev"
Requires-Dist: pytest-asyncio; extra == "dev"
Provides-Extra: transformers
Requires-Dist: transformers[torch]==4.52.4; extra == "transformers"
Provides-Extra: sherpa
Requires-Dist: sherpa-onnx==1.12.15; extra == "sherpa"
Provides-Extra: onnx-asr
Requires-Dist: onnx-asr[cpu,hub]==0.7.0; extra == "onnx-asr"
Provides-Extra: zeroconf
Requires-Dist: wyoming[zeroconf]; extra == "zeroconf"
Dynamic: license-file
